cloud/CloudAPIRequest.py
cloud/CloudApiConfig.py
cloud/CloudLogUtil.py
cloud/CloudRequestUtil.py
cloud/CloudSignUtil.py
cloud/CloudYamlUtil.py
cloud/__init__.py
cloud/cli.py
cloudapirequest-1.3.0.dist-info/LICENSE
cloudapirequest-1.3.0.dist-info/METADATA
cloudapirequest-1.3.0.dist-info/WHEEL
cloudapirequest-1.3.0.dist-info/top_level.txt
cloudapirequest-1.3.0.dist-info/RECORD
