Metadata-Version: 2.1
Name: CloudApiRequest
Version: 1.3.0
Summary: 天润cloud接口测试库
Home-page: https://www.ti-net.com.cn/
Author: 天润-测试
Author-email: wangwd@ti-net.com.cn
License: MIT
Requires-Python: >=3.7
License-File: LICENSE
Requires-Dist: Faker==18.4.0
Requires-Dist: jsonpath==0.82
Requires-Dist: pytz==2023.3
Requires-Dist: PyYAML==6.0
Requires-Dist: requests==2.28.2
Requires-Dist: allure-pytest==2.13.2
Requires-Dist: allure-python-commons==2.13.2
Requires-Dist: requests-toolbelt==1.0.0
Requires-Dist: pycryptodome==3.17
Requires-Dist: pytest-assume==2.4.3
